wave_reader/__init__.py
wave_reader/data.py
wave_reader/measure.py
wave_reader/utils.py
wave_reader/wave.py
wave_reader/web/__init__.py
wave_reader/web/client.py
wave_reader/web/types.py
wave_reader/web/api/__init__.py
wave_reader/web/api/default/__init__.py
wave_reader/web/api/default/get_consumer_api_docs.py
wave_reader/web/api/devices/__init__.py
wave_reader/web/api/devices/device_battery_history.py
wave_reader/web/api/devices/device_battery_latest_values.py
wave_reader/web/api/devices/device_info.py
wave_reader/web/api/devices/device_sample_history.py
wave_reader/web/api/devices/device_sample_history_mold.py
wave_reader/web/api/devices/device_sample_history_virus_risk.py
wave_reader/web/api/devices/device_samples_latest_values.py
wave_reader/web/api/devices/device_threshold_notifications.py
wave_reader/web/api/devices/devices_list.py
wave_reader/web/api/documentation/__init__.py
wave_reader/web/api/documentation/api_reference_json.py
wave_reader/web/api/locations/__init__.py
wave_reader/web/api/locations/add_device_to_location.py
wave_reader/web/api/locations/add_location.py
wave_reader/web/api/locations/location_info.py
wave_reader/web/api/locations/location_samples_latest_values.py
wave_reader/web/api/locations/locations_list.py
wave_reader/web/api/organizations/__init__.py
wave_reader/web/api/organizations/organizations_list.py
wave_reader/web/api/segments/__init__.py
wave_reader/web/api/segments/segment_sample_history.py
wave_reader/web/api/segments/segment_sample_history_mold.py
wave_reader/web/api/segments/segment_sample_history_virus.py
wave_reader/web/api/segments/segments_info.py
wave_reader/web/api/segments/segments_list.py
wave_reader/web/api/thresholds/__init__.py
wave_reader/web/api/thresholds/device_thresholds.py
wave_reader/web/api/webhooks/__init__.py
wave_reader/web/api/webhooks/add_webhook.py
wave_reader/web/api/webhooks/delete_webhook.py
wave_reader/web/api/webhooks/edit_webhook.py
wave_reader/web/api/webhooks/webhooks_list.py
wave_reader-1.0.2.dist-info/LICENSE.md
wave_reader-1.0.2.dist-info/METADATA
wave_reader-1.0.2.dist-info/WHEEL
wave_reader-1.0.2.dist-info/top_level.txt
wave_reader-1.0.2.dist-info/RECORD
