Metadata-Version: 2.1
Name: wave-reader
Version: 1.0.2
Summary: Unofficial package for Airthings Wave communication.
Home-page: https://github.com/ztroop/wave-reader-utils
Author: Zackary Troop
License: MIT
Classifier: Intended Audience :: Developers
Classifier: License :: OSI Approved :: MIT License
Classifier: Operating System :: OS Independent
Classifier: Programming Language :: Python :: 3.7
Classifier: Programming Language :: Python :: 3.8
Classifier: Programming Language :: Python :: 3.9
Classifier: Programming Language :: Python :: 3.10
Classifier: Programming Language :: Python :: 3.11
Requires-Python: >=3.7.0
License-File: LICENSE.md
Requires-Dist: Authlib (>=0.15.6)
Requires-Dist: bleak (>=0.19.5)
Requires-Dist: httpx (>=0.18.2)
Requires-Dist: attrs (>=21.3.0)
Requires-Dist: python-dateutil (>=2.8.2)
